{
  "_format": "hh-sol-cache-2",
  "files": {
    "/Users/thaddydore/Downloads/tijarah-lecture-materials/ballot-current-session/contracts/Balloting.sol": {
      "lastModificationDate": 1745996754599,
      "contentHash": "1e03698a9e1833110de78ef7ce5b9a41",
      "sourceName": "contracts/Balloting.sol",
      "solcConfig": {
        "version": "0.8.28",
        "settings": {
          "evmVersion": "paris",
          "optimizer": {
            "enabled": false,
            "runs": 200
          },
          "outputSelection": {
            "*": {
              "*": [
                "abi",
                "evm.bytecode",
                "evm.deployedBytecode",
                "evm.methodIdentifiers",
                "metadata"
              ],
              "": [
                "ast"
              ]
            }
          }
        }
      },
      "imports": [],
      "versionPragmas": [
        "^0.8.19"
      ],
      "artifacts": [
        "Balloting"
      ]
    },
    "/Users/thaddydore/Downloads/tijarah-lecture-materials/ballot-current-session/contracts/Lock.sol": {
      "lastModificationDate": 1745997103536,
      "contentHash": "7eee587c347fe6b1de50c96688cb9477",
      "sourceName": "contracts/Lock.sol",
      "solcConfig": {
        "version": "0.8.28",
        "settings": {
          "evmVersion": "paris",
          "optimizer": {
            "enabled": false,
            "runs": 200
          },
          "outputSelection": {
            "*": {
              "*": [
                "abi",
                "evm.bytecode",
                "evm.deployedBytecode",
                "evm.methodIdentifiers",
                "metadata"
              ],
              "": [
                "ast"
              ]
            }
          }
        }
      },
      "imports": [],
      "versionPragmas": [
        "^0.8.28"
      ],
      "artifacts": [
        "Lock"
      ]
    },
    "/Users/thaddydore/Downloads/tijarah-lecture-materials/ballot-current-session/contracts/Lottery.sol": {
      "lastModificationDate": 1745996754598,
      "contentHash": "24f116a64b23928c3f5e79e7d7b67175",
      "sourceName": "contracts/Lottery.sol",
      "solcConfig": {
        "version": "0.8.28",
        "settings": {
          "evmVersion": "paris",
          "optimizer": {
            "enabled": false,
            "runs": 200
          },
          "outputSelection": {
            "*": {
              "*": [
                "abi",
                "evm.bytecode",
                "evm.deployedBytecode",
                "evm.methodIdentifiers",
                "metadata"
              ],
              "": [
                "ast"
              ]
            }
          }
        }
      },
      "imports": [],
      "versionPragmas": [
        "^0.8.24"
      ],
      "artifacts": [
        "Lottery"
      ]
    }
  }
}
